{
	"emitters": [
		{
			"position":"9.5, 1.6, -0.8",
			"orientation":"east"
		},{
			"position":"9.5, 1.6, -1.8",
			"orientation":"east"
		},{
			"position":"9.7, 1.6, 2.0",
			"orientation":"east",
			"cover":0.8
		},{
			"position":"4.1, 5.5, -5.2",
			"orientation":"south",
			"size":2
		},{
			"position":"-4.0, 5.5, -5.2",
			"orientation":"south",
			"size":2
		},{
			"position":"-4.0, 1.6, -7.2",
			"orientation":"south"
		},{
			"position":"4.0, 1.6, -7.2",
			"orientation":"south"
		},{
			"position":"-1.2, 1.6, 8.0",
			"orientation":"north",
			"cover":0.3
		},{
			"position":"-4.0, 1.6, 8.0",
			"orientation":"north",
			"cover":0.3
		},{
			"position":"4.0, 5.5, 2.0",
			"orientation":"south",
			"size":2
		}
	],
	"periods":{
		
	},
	"options":{
		"override_shadows":"",
		"intensity_multiplier": 1.1,
		"range_multiplier": 0.8,
	}
}